[
  {
    "format_id": "format_display_banner",
    "name": "Display Banner",
    "category": "Display",
    "platform": "Web",
    "dimensions": "728x90",
    "duration": null,
    "file_types": ["jpg", "png", "gif", "html5"],
    "max_file_size": 150,
    "animation_allowed": true,
    "audio_allowed": false,
    "video_allowed": false,
    "text_overlay_allowed": true,
    "cta_required": false,
    "technical_specs": {
      "max_file_size_kb": 150,
      "color_space": "sRGB",
      "frame_rate_max": 30,
      "loop_max": 3
    },
    "pricing_model": ["CPM", "CPC"],
    "description": "Стандартный display баннер для веб-размещений",
    "is_active": true,
    "created_at": "2024-01-01T00:00:00Z",
    "updated_at": "2024-09-15T10:30:00Z"
  },
  {
    "format_id": "format_video_pre_roll",
    "name": "Video Pre-roll",
    "category": "Video",
    "platform": "YouTube",
    "dimensions": "1920x1080",
    "duration": 15,
    "file_types": ["mp4", "mov"],
    "max_file_size": 1024,
    "animation_allowed": false,
    "audio_allowed": true,
    "video_allowed": true,
    "text_overlay_allowed": true,
    "cta_required": true,
    "technical_specs": {
      "max_file_size_mb": 1024,
      "video_codec": "H.264",
      "audio_codec": "AAC",
      "frame_rate": 30,
      "bitrate_max": "8000 kbps"
    },
    "pricing_model": ["CPV", "CPM"],
    "description": "15-секундный pre-roll ролик для YouTube",
    "is_active": true,
    "created_at": "2024-01-01T00:00:00Z",
    "updated_at": "2024-09-18T14:45:00Z"
  },
  {
    "format_id": "format_social_post",
    "name": "Social Media Post",
    "category": "Social",
    "platform": "Instagram",
    "dimensions": "1080x1080",
    "duration": null,
    "file_types": ["jpg", "png"],
    "max_file_size": 30,
    "animation_allowed": false,
    "audio_allowed": false,
    "video_allowed": false,
    "text_overlay_allowed": true,
    "cta_required": false,
    "technical_specs": {
      "max_file_size_mb": 30,
      "color_space": "sRGB",
      "min_resolution": "600x600",
      "aspect_ratio": "1:1"
    },
    "pricing_model": ["CPM", "CPC", "CPA"],
    "description": "Квадратный пост для Instagram фида",
    "is_active": true,
    "created_at": "2024-01-01T00:00:00Z",
    "updated_at": "2024-09-20T11:20:00Z"
  },
  {
    "format_id": "format_social_story",
    "name": "Instagram Story",
    "category": "Social",
    "platform": "Instagram",
    "dimensions": "1080x1920",
    "duration": 15,
    "file_types": ["jpg", "png", "mp4"],
    "max_file_size": 4,
    "animation_allowed": true,
    "audio_allowed": true,
    "video_allowed": true,
    "text_overlay_allowed": true,
    "cta_required": false,
    "technical_specs": {
      "max_file_size_mb": 4,
      "aspect_ratio": "9:16",
      "video_length_max": 15,
      "frame_rate_max": 30
    },
    "pricing_model": ["CPM", "CPC"],
    "description": "Вертикальная Stories для Instagram",
    "is_active": true,
    "created_at": "2024-01-01T00:00:00Z",
    "updated_at": "2024-09-12T16:30:00Z"
  },
  {
    "format_id": "format_native_article",
    "name": "Native Article",
    "category": "Native",
    "platform": "Website",
    "dimensions": null,
    "duration": null,
    "file_types": ["html", "txt"],
    "max_file_size": null,
    "animation_allowed": false,
    "audio_allowed": false,
    "video_allowed": false,
    "text_overlay_allowed": false,
    "cta_required": true,
    "technical_specs": {
      "word_count_min": 800,
      "word_count_max": 2000,
      "images_required": 3,
      "seo_optimized": true
    },
    "pricing_model": ["Fixed", "CPM"],
    "description": "Нативная статья для медийных порталов",
    "is_active": true,
    "created_at": "2024-01-01T00:00:00Z",
    "updated_at": "2024-09-08T09:15:00Z"
  },
  {
    "format_id": "format_radio_spot",
    "name": "Radio Spot",
    "category": "Audio",
    "platform": "Radio",
    "dimensions": null,
    "duration": 30,
    "file_types": ["mp3", "wav"],
    "max_file_size": 10,
    "animation_allowed": false,
    "audio_allowed": true,
    "video_allowed": false,
    "text_overlay_allowed": false,
    "cta_required": true,
    "technical_specs": {
      "max_file_size_mb": 10,
      "audio_format": "Stereo",
      "sample_rate": "44.1 kHz",
      "bit_depth": "16-bit"
    },
    "pricing_model": ["Fixed", "CPP"],
    "description": "30-секундный радио-ролик",
    "is_active": true,
    "created_at": "2024-01-01T00:00:00Z",
    "updated_at": "2024-09-05T13:45:00Z"
  },
  {
    "format_id": "format_outdoor_billboard",
    "name": "Outdoor Billboard",
    "category": "OOH",
    "platform": "Outdoor",
    "dimensions": "6000x3000",
    "duration": null,
    "file_types": ["pdf", "eps", "ai"],
    "max_file_size": 200,
    "animation_allowed": false,
    "audio_allowed": false,
    "video_allowed": false,
    "text_overlay_allowed": true,
    "cta_required": false,
    "technical_specs": {
      "max_file_size_mb": 200,
      "color_mode": "CMYK",
      "resolution_dpi": 150,
      "bleed_mm": 5
    },
    "pricing_model": ["Fixed", "CPM"],
    "description": "Наружная реклама - билборд 6x3м",
    "is_active": true,
    "created_at": "2024-01-01T00:00:00Z",
    "updated_at": "2024-09-10T12:00:00Z"
  },
  {
    "format_id": "format_tv_commercial",
    "name": "TV Commercial",
    "category": "TV",
    "platform": "Television",
    "dimensions": "1920x1080",
    "duration": 30,
    "file_types": ["mov", "mxf"],
    "max_file_size": 5000,
    "animation_allowed": true,
    "audio_allowed": true,
    "video_allowed": true,
    "text_overlay_allowed": true,
    "cta_required": true,
    "technical_specs": {
      "max_file_size_mb": 5000,
      "video_codec": "ProRes 422",
      "audio_channels": "Stereo",
      "frame_rate": 25,
      "color_space": "Rec. 709"
    },
    "pricing_model": ["Fixed", "GRP"],
    "description": "30-секундный телевизионный ролик",
    "is_active": true,
    "created_at": "2024-01-01T00:00:00Z",
    "updated_at": "2024-09-14T15:25:00Z"
  }
]