[
  {
    "kpi_id": "kpi_001",
    "channel": "google",
    "format": "search_ads",
    "target_segment": "Мужчины 25-45, технологии",
    "period": "2024-Q4",
    "kpi_type": "CTR",
    "value": 3.2,
    "unit": "%",
    "source": "Google Ads отчет",
    "reliability": "высокий",
    "campaign_type": "lead_generation",
    "geography": "Москва",
    "budget_range": "500000-1000000",
    "sample_size": 150000,
    "confidence_interval": 95,
    "notes": "Высокие показатели для B2B сегмента",
    "created_at": "2024-12-15T10:00:00Z",
    "updated_at": "2024-12-15T10:00:00Z"
  },
  {
    "kpi_id": "kpi_002",
    "channel": "google",
    "format": "search_ads",
    "target_segment": "Мужчины 25-45, технологии",
    "period": "2024-Q4",
    "kpi_type": "CPC",
    "value": 85,
    "unit": "руб",
    "source": "Google Ads отчет",
    "reliability": "высокий",
    "campaign_type": "lead_generation",
    "geography": "Москва",
    "budget_range": "500000-1000000",
    "sample_size": 150000,
    "confidence_interval": 95,
    "notes": "Средняя стоимость клика для IT сферы",
    "created_at": "2024-12-15T10:00:00Z",
    "updated_at": "2024-12-15T10:00:00Z"
  },
  {
    "kpi_id": "kpi_003",
    "channel": "facebook",
    "format": "video_ads",
    "target_segment": "Женщины 25-35, косметика",
    "period": "2024-Q4",
    "kpi_type": "CPM",
    "value": 320,
    "unit": "руб/1000",
    "source": "Facebook Ads Manager",
    "reliability": "высокий",
    "campaign_type": "brand_awareness",
    "geography": "Россия",
    "budget_range": "1000000-3000000",
    "sample_size": 2500000,
    "confidence_interval": 98,
    "notes": "Стандартные показатели для beauty сегмента",
    "created_at": "2024-12-10T14:30:00Z",
    "updated_at": "2024-12-10T14:30:00Z"
  },
  {
    "kpi_id": "kpi_004",
    "channel": "facebook",
    "format": "video_ads",
    "target_segment": "Женщины 25-35, косметика",
    "period": "2024-Q4",
    "kpi_type": "CTR",
    "value": 2.8,
    "unit": "%",
    "source": "Facebook Ads Manager",
    "reliability": "высокий",
    "campaign_type": "brand_awareness",
    "geography": "Россия",
    "budget_range": "1000000-3000000",
    "sample_size": 2500000,
    "confidence_interval": 98,
    "notes": "Хорошая вовлеченность для видео контента",
    "created_at": "2024-12-10T14:30:00Z",
    "updated_at": "2024-12-10T14:30:00Z"
  },
  {
    "kpi_id": "kpi_005",
    "channel": "instagram",
    "format": "stories",
    "target_segment": "Молодежь 18-28, fashion",
    "period": "2024-Q3",
    "kpi_type": "CPM",
    "value": 280,
    "unit": "руб/1000",
    "source": "Meta Business Manager",
    "reliability": "высокий",
    "campaign_type": "engagement",
    "geography": "Москва, СПб",
    "budget_range": "300000-800000",
    "sample_size": 1200000,
    "confidence_interval": 95,
    "notes": "Эффективный формат для молодой аудитории",
    "created_at": "2024-10-20T09:15:00Z",
    "updated_at": "2024-10-20T09:15:00Z"
  },
  {
    "kpi_id": "kpi_006",
    "channel": "instagram",
    "format": "stories",
    "target_segment": "Молодежь 18-28, fashion",
    "period": "2024-Q3",
    "kpi_type": "completion_rate",
    "value": 78,
    "unit": "%",
    "source": "Meta Business Manager",
    "reliability": "высокий",
    "campaign_type": "engagement",
    "geography": "Москва, СПб",
    "budget_range": "300000-800000",
    "sample_size": 1200000,
    "confidence_interval": 95,
    "notes": "Высокий процент досмотра в Stories",
    "created_at": "2024-10-20T09:15:00Z",
    "updated_at": "2024-10-20T09:15:00Z"
  },
  {
    "kpi_id": "kpi_007",
    "channel": "youtube",
    "format": "video_6s",
    "target_segment": "Мужчины 30-50, автомобили",
    "period": "2024-Q4",
    "kpi_type": "CPV",
    "value": 3.2,
    "unit": "руб",
    "source": "YouTube Analytics",
    "reliability": "высокий",
    "campaign_type": "brand_awareness",
    "geography": "Россия",
    "budget_range": "2000000-5000000",
    "sample_size": 5000000,
    "confidence_interval": 99,
    "notes": "Оптимальная стоимость просмотра для automotive",
    "created_at": "2024-12-01T16:45:00Z",
    "updated_at": "2024-12-01T16:45:00Z"
  },
  {
    "kpi_id": "kpi_008",
    "channel": "youtube",
    "format": "video_6s",
    "target_segment": "Мужчины 30-50, автомобили",
    "period": "2024-Q4",
    "kpi_type": "view_rate",
    "value": 85,
    "unit": "%",
    "source": "YouTube Analytics",
    "reliability": "высокий",
    "campaign_type": "brand_awareness",
    "geography": "Россия",
    "budget_range": "2000000-5000000",
    "sample_size": 5000000,
    "confidence_interval": 99,
    "notes": "Высокий процент просмотров для 6-секундных роликов",
    "created_at": "2024-12-01T16:45:00Z",
    "updated_at": "2024-12-01T16:45:00Z"
  },
  {
    "kpi_id": "kpi_009",
    "channel": "telegram",
    "format": "channel_post",
    "target_segment": "IT специалисты 25-40",
    "period": "2024-Q4",
    "kpi_type": "ER",
    "value": 8.5,
    "unit": "%",
    "source": "Telegram Analytics",
    "reliability": "средний",
    "campaign_type": "lead_generation",
    "geography": "Россия",
    "budget_range": "200000-500000",
    "sample_size": 50000,
    "confidence_interval": 90,
    "notes": "Высокая вовлеченность в нишевых каналах",
    "created_at": "2024-11-15T12:20:00Z",
    "updated_at": "2024-11-15T12:20:00Z"
  },
  {
    "kpi_id": "kpi_010",
    "channel": "telegram",
    "format": "channel_post",
    "target_segment": "IT специалисты 25-40",
    "period": "2024-Q4",
    "kpi_type": "CPM",
    "value": 150,
    "unit": "руб/1000",
    "source": "Telegram Analytics",
    "reliability": "средний",
    "campaign_type": "lead_generation",
    "geography": "Россия",
    "budget_range": "200000-500000",
    "sample_size": 50000,
    "confidence_interval": 90,
    "notes": "Низкая стоимость охвата в профессиональных каналах",
    "created_at": "2024-11-15T12:20:00Z",
    "updated_at": "2024-11-15T12:20:00Z"
  },
  {
    "kpi_id": "kpi_011",
    "channel": "yandex",
    "format": "search_ads",
    "target_segment": "Семьи с детьми 30-45",
    "period": "2024-Q3",
    "kpi_type": "conversion_rate",
    "value": 4.2,
    "unit": "%",
    "source": "Яндекс.Директ",
    "reliability": "высокий",
    "campaign_type": "ecommerce",
    "geography": "Москва, регионы",
    "budget_range": "800000-2000000",
    "sample_size": 300000,
    "confidence_interval": 95,
    "notes": "Хорошие конверсии в семейном сегменте",
    "created_at": "2024-09-25T11:10:00Z",
    "updated_at": "2024-09-25T11:10:00Z"
  },
  {
    "kpi_id": "kpi_012",
    "channel": "vk",
    "format": "community_post",
    "target_segment": "Студенты 18-25",
    "period": "2024-Q4",
    "kpi_type": "reach_rate",
    "value": 12.3,
    "unit": "%",
    "source": "VK Ads",
    "reliability": "средний",
    "campaign_type": "engagement",
    "geography": "Россия",
    "budget_range": "100000-400000",
    "sample_size": 800000,
    "confidence_interval": 90,
    "notes": "Органический охват в студенческих сообществах",
    "created_at": "2024-12-05T15:30:00Z",
    "updated_at": "2024-12-05T15:30:00Z"
  }
]